trading212/__init__.py
trading212/http_request.py
trading212_connector-1.0.dist-info/LICENSE
trading212_connector-1.0.dist-info/METADATA
trading212_connector-1.0.dist-info/WHEEL
trading212_connector-1.0.dist-info/top_level.txt
trading212_connector-1.0.dist-info/RECORD
