Metadata-Version: 2.2
Name: trading212-connector
Version: 1.0
Author-email: Niall O'Connor <zechs.marquie@gmail.com>
Classifier: Programming Language :: Python :: 3
Classifier: License :: OSI Approved :: MIT License
Classifier: Operating System :: OS Independent
Requires-Python: >=3.7
License-File: LICENSE
Requires-Dist: requests
